<?xml version="1.0"?>
<Workbook xmlns="urn:schemas-microsoft-com:office:spreadsheet"
 xmlns:o="urn:schemas-microsoft-com:office:office"
 xmlns:x="urn:schemas-microsoft-com:office:excel"
 xmlns:ss="urn:schemas-microsoft-com:office:spreadsheet"
 xmlns:html="http://www.w3.org/TR/REC-html40">
 <DocumentProperties xmlns="urn:schemas-microsoft-com:office:office">
  <Author>arthur wu</Author>
  <LastAuthor>arthur wu</LastAuthor>
  <Created>2014-06-11T09:54:44Z</Created>
  <LastSaved>2014-06-13T02:54:37Z</LastSaved>
  <Company>le zhi of zhuhai</Company>
  <Version>14.0</Version>
 </DocumentProperties>
 <OfficeDocumentSettings xmlns="urn:schemas-microsoft-com:office:office">
  <AllowPNG/>
 </OfficeDocumentSettings>
 <ExcelWorkbook xmlns="urn:schemas-microsoft-com:office:excel">
  <WindowHeight>15980</WindowHeight>
  <WindowWidth>22320</WindowWidth>
  <WindowTopX>2540</WindowTopX>
  <WindowTopY>0</WindowTopY>
  <ProtectStructure>False</ProtectStructure>
  <ProtectWindows>False</ProtectWindows>
 </ExcelWorkbook>
 <Styles>
  <Style ss:ID="Default" ss:Name="Normal">
   <Alignment ss:Vertical="Bottom"/>
   <Borders/>
   <Font ss:FontName="宋体" x:CharSet="134" x:Family="Swiss" ss:Size="16"
    ss:Color="#000000"/>
   <Interior/>
   <NumberFormat/>
   <Protection/>
  </Style>
  <Style ss:ID="s62">
   <NumberFormat ss:Format="@"/>
  </Style>
  <Style ss:ID="s63">
   <NumberFormat ss:Format="m&quot;月&quot;d&quot;日&quot;"/>
  </Style>
 </Styles>
 <Worksheet ss:Name="世界杯每日比赛场次">
  <Table ss:ExpandedColumnCount="7" ss:ExpandedRowCount="49" x:FullColumns="1"
   x:FullRows="1" ss:DefaultColumnWidth="97" ss:DefaultRowHeight="19">
   <Column ss:Index="2" ss:AutoFitWidth="0" ss:Width="155"/>
   <Column ss:Index="4" ss:Width="116"/>
   <Column ss:Width="100"/>
   <Column ss:Index="7" ss:StyleID="s62" ss:AutoFitWidth="0"/>
   <Row ss:AutoFitHeight="0">
    <Cell><Data ss:Type="String">序号</Data></Cell>
    <Cell><Data ss:Type="String">比赛日期</Data></Cell>
    <Cell><Data ss:Type="String">主队</Data></Cell>
    <Cell><Data ss:Type="String">客队</Data></Cell>
    <Cell><Data ss:Type="String">魔石奖励</Data></Cell>
    <Cell><Data ss:Type="String">结果</Data><Comment ss:Author="arthur wu"><Data><Font
        html:Size="10" html:Color="#000000"
        xmlns="http://www.w3.org/TR/REC-html40">比赛结果：&#13;1 = 胜&#13;2 = 平&#13;3 = 败&#13;</Font></Data></Comment></Cell>
    <Cell><Data ss:Type="String">比分</Data><Comment ss:Author="arthur wu"><Data><Font
        html:Size="10" html:Color="#000000"
        xmlns="http://www.w3.org/TR/REC-html40">比分结果：&#13;主队进球数：客队进球数&#13;例如：3:2</Font></Data></Comment></Cell>
   </Row>
   <Row ss:AutoFitHeight="0">
    <Cell><Data ss:Type="String">id</Data></Cell>
    <Cell><Data ss:Type="String">date</Data></Cell>
    <Cell><Data ss:Type="String">home_team</Data><Comment ss:Author="arthur wu"><Data><Font
        html:Size="10" html:Color="#000000"
        xmlns="http://www.w3.org/TR/REC-html40">国家列表|country|id&#13;</Font></Data></Comment></Cell>
    <Cell><Data ss:Type="String">visiting_team</Data><Comment ss:Author="arthur wu"><Data><B
        xmlns="http://www.w3.org/TR/REC-html40"><Font html:Size="10"
         html:Color="#000000">国家列表|country|id</Font></B></Data></Comment></Cell>
    <Cell><Data ss:Type="String">reward_gold</Data></Cell>
    <Cell><Data ss:Type="String">result</Data></Cell>
    <Cell><Data ss:Type="String">score</Data></Cell>
   </Row>
   <Row ss:AutoFitHeight="0">
    <Cell><Data ss:Type="Number">1</Data></Cell>
    <Cell ss:StyleID="s63"><Data ss:Type="DateTime">2014-06-14T00:00:00.000</Data></Cell>
    <Cell><Data ss:Type="String">墨西哥</Data></Cell>
    <Cell><Data ss:Type="String">喀麦隆</Data></Cell>
    <Cell><Data ss:Type="Number">20</Data></Cell>
   </Row>
   <Row ss:AutoFitHeight="0">
    <Cell><Data ss:Type="Number">2</Data></Cell>
    <Cell ss:StyleID="s63"><Data ss:Type="DateTime">2014-06-14T00:00:00.000</Data></Cell>
    <Cell><Data ss:Type="String">西班牙</Data></Cell>
    <Cell><Data ss:Type="String">荷兰</Data></Cell>
    <Cell><Data ss:Type="Number">20</Data></Cell>
   </Row>
   <Row ss:AutoFitHeight="0">
    <Cell><Data ss:Type="Number">3</Data></Cell>
    <Cell ss:StyleID="s63"><Data ss:Type="DateTime">2014-06-14T00:00:00.000</Data></Cell>
    <Cell><Data ss:Type="String">智利</Data></Cell>
    <Cell><Data ss:Type="String">澳大利亚</Data></Cell>
    <Cell><Data ss:Type="Number">20</Data></Cell>
   </Row>
   <Row ss:AutoFitHeight="0">
    <Cell><Data ss:Type="Number">4</Data></Cell>
    <Cell ss:StyleID="s63"><Data ss:Type="DateTime">2014-06-15T00:00:00.000</Data></Cell>
    <Cell><Data ss:Type="String">哥伦比亚</Data></Cell>
    <Cell><Data ss:Type="String">希腊</Data></Cell>
    <Cell><Data ss:Type="Number">20</Data></Cell>
   </Row>
   <Row ss:AutoFitHeight="0">
    <Cell><Data ss:Type="Number">5</Data></Cell>
    <Cell ss:StyleID="s63"><Data ss:Type="DateTime">2014-06-15T00:00:00.000</Data></Cell>
    <Cell><Data ss:Type="String">乌拉圭</Data></Cell>
    <Cell><Data ss:Type="String">哥斯达黎加</Data></Cell>
    <Cell><Data ss:Type="Number">20</Data></Cell>
   </Row>
   <Row ss:AutoFitHeight="0">
    <Cell><Data ss:Type="Number">6</Data></Cell>
    <Cell ss:StyleID="s63"><Data ss:Type="DateTime">2014-06-15T00:00:00.000</Data></Cell>
    <Cell><Data ss:Type="String">英格兰</Data></Cell>
    <Cell><Data ss:Type="String">意大利</Data></Cell>
    <Cell><Data ss:Type="Number">20</Data></Cell>
   </Row>
   <Row ss:AutoFitHeight="0">
    <Cell><Data ss:Type="Number">7</Data></Cell>
    <Cell ss:StyleID="s63"><Data ss:Type="DateTime">2014-06-15T00:00:00.000</Data></Cell>
    <Cell><Data ss:Type="String">科特迪瓦</Data></Cell>
    <Cell><Data ss:Type="String">日本</Data></Cell>
    <Cell><Data ss:Type="Number">20</Data></Cell>
   </Row>
   <Row ss:AutoFitHeight="0">
    <Cell><Data ss:Type="Number">8</Data></Cell>
    <Cell ss:StyleID="s63"><Data ss:Type="DateTime">2014-06-16T00:00:00.000</Data></Cell>
    <Cell><Data ss:Type="String">瑞士</Data></Cell>
    <Cell><Data ss:Type="String">厄瓜多尔</Data></Cell>
    <Cell><Data ss:Type="Number">20</Data></Cell>
   </Row>
   <Row ss:AutoFitHeight="0">
    <Cell><Data ss:Type="Number">9</Data></Cell>
    <Cell ss:StyleID="s63"><Data ss:Type="DateTime">2014-06-16T00:00:00.000</Data></Cell>
    <Cell ss:HRef="http://2014.sina.com.cn/teams/france.html"><Data
      ss:Type="String">法国</Data></Cell>
    <Cell><Data ss:Type="String">洪都拉斯</Data></Cell>
    <Cell><Data ss:Type="Number">20</Data></Cell>
   </Row>
   <Row ss:AutoFitHeight="0">
    <Cell><Data ss:Type="Number">10</Data></Cell>
    <Cell ss:StyleID="s63"><Data ss:Type="DateTime">2014-06-16T00:00:00.000</Data></Cell>
    <Cell><Data ss:Type="String">阿根廷</Data></Cell>
    <Cell><Data ss:Type="String">波黑</Data></Cell>
    <Cell><Data ss:Type="Number">20</Data></Cell>
   </Row>
   <Row ss:AutoFitHeight="0">
    <Cell><Data ss:Type="Number">11</Data></Cell>
    <Cell ss:StyleID="s63"><Data ss:Type="DateTime">2014-06-17T00:00:00.000</Data></Cell>
    <Cell><Data ss:Type="String">德国</Data></Cell>
    <Cell><Data ss:Type="String">葡萄牙</Data></Cell>
    <Cell><Data ss:Type="Number">20</Data></Cell>
   </Row>
   <Row ss:AutoFitHeight="0">
    <Cell><Data ss:Type="Number">12</Data></Cell>
    <Cell ss:StyleID="s63"><Data ss:Type="DateTime">2014-06-17T00:00:00.000</Data></Cell>
    <Cell><Data ss:Type="String">伊朗</Data></Cell>
    <Cell><Data ss:Type="String">尼日利亚</Data></Cell>
    <Cell><Data ss:Type="Number">20</Data></Cell>
   </Row>
   <Row ss:AutoFitHeight="0">
    <Cell><Data ss:Type="Number">13</Data></Cell>
    <Cell ss:StyleID="s63"><Data ss:Type="DateTime">2014-06-17T00:00:00.000</Data></Cell>
    <Cell><Data ss:Type="String">加纳</Data></Cell>
    <Cell><Data ss:Type="String">美国</Data></Cell>
    <Cell><Data ss:Type="Number">20</Data></Cell>
   </Row>
   <Row ss:AutoFitHeight="0">
    <Cell><Data ss:Type="Number">14</Data></Cell>
    <Cell ss:StyleID="s63"><Data ss:Type="DateTime">2014-06-18T00:00:00.000</Data></Cell>
    <Cell><Data ss:Type="String">比利时</Data></Cell>
    <Cell><Data ss:Type="String">阿尔及利亚</Data></Cell>
    <Cell><Data ss:Type="Number">20</Data></Cell>
   </Row>
   <Row ss:AutoFitHeight="0">
    <Cell><Data ss:Type="Number">15</Data></Cell>
    <Cell ss:StyleID="s63"><Data ss:Type="DateTime">2014-06-18T00:00:00.000</Data></Cell>
    <Cell><Data ss:Type="String">巴西</Data></Cell>
    <Cell><Data ss:Type="String">墨西哥</Data></Cell>
    <Cell><Data ss:Type="Number">20</Data></Cell>
   </Row>
   <Row ss:AutoFitHeight="0">
    <Cell><Data ss:Type="Number">16</Data></Cell>
    <Cell ss:StyleID="s63"><Data ss:Type="DateTime">2014-06-18T00:00:00.000</Data></Cell>
    <Cell><Data ss:Type="String">俄罗斯</Data></Cell>
    <Cell><Data ss:Type="String">韩国</Data></Cell>
    <Cell><Data ss:Type="Number">20</Data></Cell>
   </Row>
   <Row ss:AutoFitHeight="0">
    <Cell><Data ss:Type="Number">17</Data></Cell>
    <Cell ss:StyleID="s63"><Data ss:Type="DateTime">2014-06-19T00:00:00.000</Data></Cell>
    <Cell><Data ss:Type="String">澳大利亚</Data></Cell>
    <Cell><Data ss:Type="String">荷兰</Data></Cell>
    <Cell><Data ss:Type="Number">20</Data></Cell>
   </Row>
   <Row ss:AutoFitHeight="0">
    <Cell><Data ss:Type="Number">18</Data></Cell>
    <Cell ss:StyleID="s63"><Data ss:Type="DateTime">2014-06-19T00:00:00.000</Data></Cell>
    <Cell><Data ss:Type="String">西班牙</Data></Cell>
    <Cell><Data ss:Type="String">智利</Data></Cell>
    <Cell><Data ss:Type="Number">20</Data></Cell>
   </Row>
   <Row ss:AutoFitHeight="0">
    <Cell><Data ss:Type="Number">19</Data></Cell>
    <Cell ss:StyleID="s63"><Data ss:Type="DateTime">2014-06-19T00:00:00.000</Data></Cell>
    <Cell><Data ss:Type="String">喀麦隆</Data></Cell>
    <Cell><Data ss:Type="String">克罗地亚</Data></Cell>
    <Cell><Data ss:Type="Number">20</Data></Cell>
   </Row>
   <Row ss:AutoFitHeight="0">
    <Cell><Data ss:Type="Number">20</Data></Cell>
    <Cell ss:StyleID="s63"><Data ss:Type="DateTime">2014-06-20T00:00:00.000</Data></Cell>
    <Cell><Data ss:Type="String">哥伦比亚</Data></Cell>
    <Cell><Data ss:Type="String">科特迪瓦</Data></Cell>
    <Cell><Data ss:Type="Number">20</Data></Cell>
   </Row>
   <Row ss:AutoFitHeight="0">
    <Cell><Data ss:Type="Number">21</Data></Cell>
    <Cell ss:StyleID="s63"><Data ss:Type="DateTime">2014-06-20T00:00:00.000</Data></Cell>
    <Cell><Data ss:Type="String">乌拉圭</Data></Cell>
    <Cell><Data ss:Type="String">英格兰</Data></Cell>
    <Cell><Data ss:Type="Number">20</Data></Cell>
   </Row>
   <Row ss:AutoFitHeight="0">
    <Cell><Data ss:Type="Number">22</Data></Cell>
    <Cell ss:StyleID="s63"><Data ss:Type="DateTime">2014-06-20T00:00:00.000</Data></Cell>
    <Cell><Data ss:Type="String">日本</Data></Cell>
    <Cell><Data ss:Type="String">希腊</Data></Cell>
    <Cell><Data ss:Type="Number">20</Data></Cell>
   </Row>
   <Row ss:AutoFitHeight="0">
    <Cell><Data ss:Type="Number">23</Data></Cell>
    <Cell ss:StyleID="s63"><Data ss:Type="DateTime">2014-06-21T00:00:00.000</Data></Cell>
    <Cell><Data ss:Type="String">意大利</Data></Cell>
    <Cell><Data ss:Type="String">哥斯达黎加</Data></Cell>
    <Cell><Data ss:Type="Number">20</Data></Cell>
   </Row>
   <Row ss:AutoFitHeight="0">
    <Cell><Data ss:Type="Number">24</Data></Cell>
    <Cell ss:StyleID="s63"><Data ss:Type="DateTime">2014-06-21T00:00:00.000</Data></Cell>
    <Cell><Data ss:Type="String">瑞士</Data></Cell>
    <Cell><Data ss:Type="String">法国</Data></Cell>
    <Cell><Data ss:Type="Number">20</Data></Cell>
   </Row>
   <Row ss:AutoFitHeight="0">
    <Cell><Data ss:Type="Number">25</Data></Cell>
    <Cell ss:StyleID="s63"><Data ss:Type="DateTime">2014-06-21T00:00:00.000</Data></Cell>
    <Cell><Data ss:Type="String">洪都拉斯</Data></Cell>
    <Cell><Data ss:Type="String">厄瓜多尔</Data></Cell>
    <Cell><Data ss:Type="Number">20</Data></Cell>
   </Row>
   <Row ss:AutoFitHeight="0">
    <Cell><Data ss:Type="Number">26</Data></Cell>
    <Cell ss:StyleID="s63"><Data ss:Type="DateTime">2014-06-22T00:00:00.000</Data></Cell>
    <Cell><Data ss:Type="String">阿根廷</Data></Cell>
    <Cell><Data ss:Type="String">伊朗</Data></Cell>
    <Cell><Data ss:Type="Number">20</Data></Cell>
   </Row>
   <Row ss:AutoFitHeight="0">
    <Cell><Data ss:Type="Number">27</Data></Cell>
    <Cell ss:StyleID="s63"><Data ss:Type="DateTime">2014-06-22T00:00:00.000</Data></Cell>
    <Cell><Data ss:Type="String">德国</Data></Cell>
    <Cell><Data ss:Type="String">加纳</Data></Cell>
    <Cell><Data ss:Type="Number">20</Data></Cell>
   </Row>
   <Row ss:AutoFitHeight="0">
    <Cell><Data ss:Type="Number">28</Data></Cell>
    <Cell ss:StyleID="s63"><Data ss:Type="DateTime">2014-06-22T00:00:00.000</Data></Cell>
    <Cell><Data ss:Type="String">尼日利亚</Data></Cell>
    <Cell><Data ss:Type="String">波黑</Data></Cell>
    <Cell><Data ss:Type="Number">20</Data></Cell>
   </Row>
   <Row ss:AutoFitHeight="0">
    <Cell><Data ss:Type="Number">29</Data></Cell>
    <Cell ss:StyleID="s63"><Data ss:Type="DateTime">2014-06-23T00:00:00.000</Data></Cell>
    <Cell><Data ss:Type="String">比利时</Data></Cell>
    <Cell><Data ss:Type="String">俄罗斯</Data></Cell>
    <Cell><Data ss:Type="Number">20</Data></Cell>
   </Row>
   <Row ss:AutoFitHeight="0">
    <Cell><Data ss:Type="Number">30</Data></Cell>
    <Cell ss:StyleID="s63"><Data ss:Type="DateTime">2014-06-23T00:00:00.000</Data></Cell>
    <Cell><Data ss:Type="String">韩国</Data></Cell>
    <Cell><Data ss:Type="String">阿尔及利亚</Data></Cell>
    <Cell><Data ss:Type="Number">20</Data></Cell>
   </Row>
   <Row ss:AutoFitHeight="0">
    <Cell><Data ss:Type="Number">31</Data></Cell>
    <Cell ss:StyleID="s63"><Data ss:Type="DateTime">2014-06-23T00:00:00.000</Data></Cell>
    <Cell><Data ss:Type="String">美国</Data></Cell>
    <Cell><Data ss:Type="String">葡萄牙</Data></Cell>
    <Cell><Data ss:Type="Number">20</Data></Cell>
   </Row>
   <Row ss:AutoFitHeight="0">
    <Cell><Data ss:Type="Number">32</Data></Cell>
    <Cell ss:StyleID="s63"><Data ss:Type="DateTime">2014-06-24T00:00:00.000</Data></Cell>
    <Cell><Data ss:Type="String">澳大利亚</Data></Cell>
    <Cell><Data ss:Type="String">西班牙</Data></Cell>
    <Cell><Data ss:Type="Number">20</Data></Cell>
   </Row>
   <Row ss:AutoFitHeight="0">
    <Cell><Data ss:Type="Number">33</Data></Cell>
    <Cell ss:StyleID="s63"><Data ss:Type="DateTime">2014-06-24T00:00:00.000</Data></Cell>
    <Cell><Data ss:Type="String">荷兰</Data></Cell>
    <Cell><Data ss:Type="String">智利</Data></Cell>
    <Cell><Data ss:Type="Number">20</Data></Cell>
   </Row>
   <Row ss:AutoFitHeight="0">
    <Cell><Data ss:Type="Number">34</Data></Cell>
    <Cell ss:StyleID="s63"><Data ss:Type="DateTime">2014-06-24T00:00:00.000</Data></Cell>
    <Cell><Data ss:Type="String">喀麦隆</Data></Cell>
    <Cell><Data ss:Type="String">巴西</Data></Cell>
    <Cell><Data ss:Type="Number">20</Data></Cell>
   </Row>
   <Row ss:AutoFitHeight="0">
    <Cell><Data ss:Type="Number">35</Data></Cell>
    <Cell ss:StyleID="s63"><Data ss:Type="DateTime">2014-06-24T00:00:00.000</Data></Cell>
    <Cell><Data ss:Type="String">克罗地亚</Data></Cell>
    <Cell><Data ss:Type="String">墨西哥</Data></Cell>
    <Cell><Data ss:Type="Number">20</Data></Cell>
   </Row>
   <Row ss:AutoFitHeight="0">
    <Cell><Data ss:Type="Number">36</Data></Cell>
    <Cell ss:StyleID="s63"><Data ss:Type="DateTime">2014-06-25T00:00:00.000</Data></Cell>
    <Cell><Data ss:Type="String">意大利</Data></Cell>
    <Cell><Data ss:Type="String">乌拉圭</Data></Cell>
    <Cell><Data ss:Type="Number">20</Data></Cell>
   </Row>
   <Row ss:AutoFitHeight="0">
    <Cell><Data ss:Type="Number">37</Data></Cell>
    <Cell ss:StyleID="s63"><Data ss:Type="DateTime">2014-06-25T00:00:00.000</Data></Cell>
    <Cell><Data ss:Type="String">哥斯达黎加</Data></Cell>
    <Cell><Data ss:Type="String">英格兰</Data></Cell>
    <Cell><Data ss:Type="Number">20</Data></Cell>
   </Row>
   <Row ss:AutoFitHeight="0">
    <Cell><Data ss:Type="Number">38</Data></Cell>
    <Cell ss:StyleID="s63"><Data ss:Type="DateTime">2014-06-25T00:00:00.000</Data></Cell>
    <Cell><Data ss:Type="String">日本</Data></Cell>
    <Cell><Data ss:Type="String">哥伦比亚</Data></Cell>
    <Cell><Data ss:Type="Number">20</Data></Cell>
   </Row>
   <Row ss:AutoFitHeight="0">
    <Cell><Data ss:Type="Number">39</Data></Cell>
    <Cell ss:StyleID="s63"><Data ss:Type="DateTime">2014-06-25T00:00:00.000</Data></Cell>
    <Cell><Data ss:Type="String">希腊</Data></Cell>
    <Cell><Data ss:Type="String">科特迪瓦</Data></Cell>
    <Cell><Data ss:Type="Number">20</Data></Cell>
   </Row>
   <Row ss:AutoFitHeight="0">
    <Cell><Data ss:Type="Number">40</Data></Cell>
    <Cell ss:StyleID="s63"><Data ss:Type="DateTime">2014-06-26T00:00:00.000</Data></Cell>
    <Cell><Data ss:Type="String">尼日利亚</Data></Cell>
    <Cell><Data ss:Type="String">阿根廷</Data></Cell>
    <Cell><Data ss:Type="Number">20</Data></Cell>
   </Row>
   <Row ss:AutoFitHeight="0">
    <Cell><Data ss:Type="Number">41</Data></Cell>
    <Cell ss:StyleID="s63"><Data ss:Type="DateTime">2014-06-26T00:00:00.000</Data></Cell>
    <Cell><Data ss:Type="String">波黑</Data></Cell>
    <Cell><Data ss:Type="String">伊朗</Data></Cell>
    <Cell><Data ss:Type="Number">20</Data></Cell>
   </Row>
   <Row ss:AutoFitHeight="0">
    <Cell><Data ss:Type="Number">42</Data></Cell>
    <Cell ss:StyleID="s63"><Data ss:Type="DateTime">2014-06-26T00:00:00.000</Data></Cell>
    <Cell><Data ss:Type="String">洪都拉斯</Data></Cell>
    <Cell><Data ss:Type="String">瑞士</Data></Cell>
    <Cell><Data ss:Type="Number">20</Data></Cell>
   </Row>
   <Row ss:AutoFitHeight="0">
    <Cell><Data ss:Type="Number">43</Data></Cell>
    <Cell ss:StyleID="s63"><Data ss:Type="DateTime">2014-06-26T00:00:00.000</Data></Cell>
    <Cell><Data ss:Type="String">厄瓜多尔</Data></Cell>
    <Cell><Data ss:Type="String">法国</Data></Cell>
    <Cell><Data ss:Type="Number">20</Data></Cell>
   </Row>
   <Row ss:AutoFitHeight="0">
    <Cell><Data ss:Type="Number">44</Data></Cell>
    <Cell ss:StyleID="s63"><Data ss:Type="DateTime">2014-06-27T00:00:00.000</Data></Cell>
    <Cell><Data ss:Type="String">美国</Data></Cell>
    <Cell><Data ss:Type="String">德国</Data></Cell>
    <Cell><Data ss:Type="Number">20</Data></Cell>
   </Row>
   <Row ss:AutoFitHeight="0">
    <Cell><Data ss:Type="Number">45</Data></Cell>
    <Cell ss:StyleID="s63"><Data ss:Type="DateTime">2014-06-27T00:00:00.000</Data></Cell>
    <Cell><Data ss:Type="String">葡萄牙</Data></Cell>
    <Cell><Data ss:Type="String">加纳</Data></Cell>
    <Cell><Data ss:Type="Number">20</Data></Cell>
   </Row>
   <Row ss:AutoFitHeight="0">
    <Cell><Data ss:Type="Number">46</Data></Cell>
    <Cell ss:StyleID="s63"><Data ss:Type="DateTime">2014-06-27T00:00:00.000</Data></Cell>
    <Cell><Data ss:Type="String">韩国</Data></Cell>
    <Cell><Data ss:Type="String">比利时</Data></Cell>
    <Cell><Data ss:Type="Number">20</Data></Cell>
   </Row>
   <Row ss:AutoFitHeight="0">
    <Cell><Data ss:Type="Number">47</Data></Cell>
    <Cell ss:StyleID="s63"><Data ss:Type="DateTime">2014-06-27T00:00:00.000</Data></Cell>
    <Cell><Data ss:Type="String">阿尔及利亚</Data></Cell>
    <Cell><Data ss:Type="String">俄罗斯</Data></Cell>
    <Cell><Data ss:Type="Number">20</Data></Cell>
   </Row>
  </Table>
  <WorksheetOptions xmlns="urn:schemas-microsoft-com:office:excel">
   <Unsynced/>
   <Print>
    <ValidPrinterInfo/>
    <PaperSizeIndex>9</PaperSizeIndex>
    <HorizontalResolution>-4</HorizontalResolution>
    <VerticalResolution>-4</VerticalResolution>
   </Print>
   <PageLayoutZoom>0</PageLayoutZoom>
   <Selected/>
   <Panes>
    <Pane>
     <Number>3</Number>
     <ActiveRow>5</ActiveRow>
     <ActiveCol>6</ActiveCol>
    </Pane>
   </Panes>
   <ProtectObjects>False</ProtectObjects>
   <ProtectScenarios>False</ProtectScenarios>
  </WorksheetOptions>
 </Worksheet>
 <Worksheet ss:Name="export">
  <Table ss:ExpandedColumnCount="3" ss:ExpandedRowCount="2" x:FullColumns="1"
   x:FullRows="1" ss:DefaultColumnWidth="97" ss:DefaultRowHeight="19">
   <Column ss:Width="156"/>
   <Column ss:Width="148"/>
   <Row ss:AutoFitHeight="0">
    <Cell><Data ss:Type="String">sheet_name</Data></Cell>
    <Cell><Data ss:Type="String">export_name</Data></Cell>
    <Cell><Data ss:Type="String">merge_to</Data></Cell>
   </Row>
   <Row ss:AutoFitHeight="0">
    <Cell><Data ss:Type="String">世界杯每日比赛场次</Data></Cell>
    <Cell><Data ss:Type="String">against_time_list</Data></Cell>
   </Row>
  </Table>
  <WorksheetOptions xmlns="urn:schemas-microsoft-com:office:excel">
   <Unsynced/>
   <Print>
    <ValidPrinterInfo/>
    <PaperSizeIndex>9</PaperSizeIndex>
    <HorizontalResolution>-4</HorizontalResolution>
    <VerticalResolution>-4</VerticalResolution>
   </Print>
   <PageLayoutZoom>0</PageLayoutZoom>
   <Panes>
    <Pane>
     <Number>3</Number>
     <ActiveRow>1</ActiveRow>
     <ActiveCol>1</ActiveCol>
    </Pane>
   </Panes>
   <ProtectObjects>False</ProtectObjects>
   <ProtectScenarios>False</ProtectScenarios>
  </WorksheetOptions>
 </Worksheet>
</Workbook>
